crm/agents/sb3/sac/__init__.py
crm/agents/sb3/sac/csac.py
crm/agents/sb3/vec/__init__.py
crm/agents/sb3/vec/subproc.py
crm/agents/tabular/__init__.py
crm/agents/tabular/cql.py
crm/agents/tabular/ql.py
crm/automaton/__init__.py
crm/automaton/compiler.py
crm/automaton/machine.py
crm/crossproduct/__init__.py
crm/crossproduct/crossproduct.py
crm/label/__init__.py
crm/label/function.py
counting_reward_machines-0.0.3.dist-info/METADATA
counting_reward_machines-0.0.3.dist-info/WHEEL
counting_reward_machines-0.0.3.dist-info/licenses/LICENSE
counting_reward_machines-0.0.3.dist-info/RECORD
