Metadata-Version: 2.4
Name: counting-reward-machines
Version: 0.0.3
Summary: The official Python library for Counting Reward Machines.
Author-email: Tristan Bester <tristanbester@email.com>
License-File: LICENSE
Requires-Python: <3.13,>=3.10
Requires-Dist: cloudpickle==3.0.0
Requires-Dist: gymnasium==0.29.1
Requires-Dist: huggingface-sb3>=3.0
Requires-Dist: hydra-core>=1.3.2
Requires-Dist: numpy==1.26.4
Requires-Dist: stable-baselines3>=2.3.2
Requires-Dist: torch==2.4.1
Requires-Dist: tqdm>=4.67.1
Provides-Extra: experiments
Requires-Dist: hydra-core>=1.3.2; extra == 'experiments'
Requires-Dist: moviepy>=2.1.1; extra == 'experiments'
Requires-Dist: panda-gym>=3.0.7; extra == 'experiments'
Requires-Dist: tbparse>=0.0.9; extra == 'experiments'
Requires-Dist: tensorboard>=2.18.0; extra == 'experiments'
Requires-Dist: wandb>=0.19.0; extra == 'experiments'
